deb/__init__.py
deb/main.py
debi-1.0.5.dist-info/LICENSE
debi-1.0.5.dist-info/METADATA
debi-1.0.5.dist-info/WHEEL
debi-1.0.5.dist-info/entry_points.txt
debi-1.0.5.dist-info/top_level.txt
debi-1.0.5.dist-info/RECORD
