Metadata-Version: 2.1
Name: debi
Version: 1.0.5
Summary: download and install deb packages from github and other resources
Home-page: https://github.com/jakbin/deb
Author: Jak Bin
Author-email: jakbin4747@gmail.com
License: MIT License
Keywords: deb,debian,github
Platform: UNKNOWN
Classifier: Programming Language :: Python :: 3.6
Classifier: License :: OSI Approved :: MIT License
Classifier: Natural Language :: English
Classifier: Operating System :: OS Independent
Requires-Python: >=3
License-File: LICENSE
Requires-Dist: tqdm
